conda_package_streaming/__init__.py
conda_package_streaming/exceptions.py
conda_package_streaming/extract.py
conda_package_streaming/lazy_wheel.py
conda_package_streaming/package_streaming.py
conda_package_streaming/s3.py
conda_package_streaming/transmute.py
conda_package_streaming/url.py
conda_package_streaming-0.6.1.dist-info/LICENSE
conda_package_streaming-0.6.1.dist-info/WHEEL
conda_package_streaming-0.6.1.dist-info/METADATA
conda_package_streaming-0.6.1.dist-info/RECORD
