Metadata-Version: 2.1
Name: conda_package_streaming
Version: 0.6.1
Summary: Download metadata from conda packages without transferring entire file.
Author-email: "Anaconda, Inc. & Contributors" <conda@continuum.io>
Requires-Python: >=3.7
Requires-Dist: requests
Requires-Dist: zstandard >=0.15
Requires-Dist: furo ; extra == "docs"
Requires-Dist: sphinx ; extra == "docs"
Requires-Dist: myst-parser ; extra == "docs"
Requires-Dist: mdit-py-plugins>=0.3.0 ; extra == "docs"
Requires-Dist: pytest >=7 ; extra == "test"
Requires-Dist: pytest-cov ; extra == "test"
Requires-Dist: pytest-mock ; extra == "test"
Requires-Dist: boto3 ; extra == "test"
Requires-Dist: boto3-stubs[essential] ; extra == "test"
Requires-Dist: bottle ; extra == "test"
Project-URL: Documentation, https://conda.github.io/conda-package-streaming/
Project-URL: Home, https://github.com/conda/conda-package-streaming
Provides-Extra: docs
Provides-Extra: test
